ppnotify/__init__.py
ppnotify/__main__.py
ppnotify/__version__.py
ppnotify/main.py
ppnotify/slack.py
ppnotify/teams.py
ppnotify-0.0.4.dist-info/licenses/LICENSE.txt
ppnotify-0.0.4.dist-info/METADATA
ppnotify-0.0.4.dist-info/WHEEL
ppnotify-0.0.4.dist-info/entry_points.txt
ppnotify-0.0.4.dist-info/top_level.txt
ppnotify-0.0.4.dist-info/RECORD
