Metadata-Version: 2.4
Name: ppnotify
Version: 0.0.4
Summary: Tool to send notifications
Author-email: Peter Pakos <peter@pakos.uk>
License: GPLv3
Project-URL: GitHub, https://github.com/peterpakos/ppnotify/
Project-URL: PyPI, https://pypi.org/project/ppnotify/
Keywords: slack,teams,message,notification,notify
Classifier: Programming Language :: Python :: 3
Classifier: Programming Language :: Python :: 3.8
Classifier: Programming Language :: Python :: 3.9
Classifier: Programming Language :: Python :: 3.10
Classifier: Programming Language :: Python :: 3.11
Classifier: Programming Language :: Python :: 3.12
Classifier: Programming Language :: Python :: 3.13
Classifier: Programming Language :: Python :: 3.14
Classifier: License :: OSI Approved :: GNU General Public License v3 (GPLv3)
Classifier: Topic :: Communications :: Chat
Requires-Python: >=3.8
License-File: LICENSE.txt
Requires-Dist: pplogger
Requires-Dist: ppconfig
Requires-Dist: slack_sdk
Requires-Dist: requests
Dynamic: license-file
